{
    "generalSituation": "高空反氣旋會在未來數天為廣東地區帶來酷熱的天氣。預料現時位於菲律賓以東海域的低壓區會發展為熱帶氣旋並逐漸增強，未來數天移向呂宋以東一帶，下週初至中期較有可能進入南海北部，並在下週中至後期為華南沿岸帶來不穩定天氣，但該系統的路徑仍存變數，亦有機會移向台灣一帶。",
    "weatherForecast": [{
        "forecastDate": "20230721",
        "week": "星期五",
        "forecastWind": "東南風2至3級。",
        "forecastWeather": "大致天晴及酷熱，但局部地區有驟雨。",
        "forecastMaxtemp": {
            "value": 33,
            "unit": "C"
        },
        "forecastMintemp": {
            "value": 28,
            "unit": "C"
        },
        "forecastMaxrh": {
            "value": 90,
            "unit": "percent"
        },
        "forecastMinrh": {
            "value": 65,
            "unit": "percent"
        },
        "ForecastIcon": 90,
        "PSR": "低"
    }, {
        "forecastDate": "20230722",
        "week": "星期六",
        "forecastWind": "東南風3級。",
        "forecastWeather": "大致天晴及酷熱，但局部地區有驟雨。",
        "forecastMaxtemp": {
            "value": 33,
            "unit": "C"
        },
        "forecastMintemp": {
            "value": 28,
            "unit": "C"
        },
        "forecastMaxrh": {
            "value": 90,
            "unit": "percent"
        },
        "forecastMinrh": {
            "value": 65,
            "unit": "percent"
        },
        "ForecastIcon": 90,
        "PSR": "低"
    }, {
        "forecastDate": "20230723",
        "week": "星期日",
        "forecastWind": "南至東南風2至3級。",
        "forecastWeather": "大致天晴及酷熱，但局部地區有驟雨。",
        "forecastMaxtemp": {
            "value": 33,
            "unit": "C"
        },
        "forecastMintemp": {
            "value": 28,
            "unit": "C"
        },
        "forecastMaxrh": {
            "value": 90,
            "unit": "percent"
        },
        "forecastMinrh": {
            "value": 65,
            "unit": "percent"
        },
        "ForecastIcon": 90,
        "PSR": "低"
    }, {
        "forecastDate": "20230724",
        "week": "星期一",
        "forecastWind": "微風2級。",
        "forecastWeather": "大致天晴及酷熱。",
        "forecastMaxtemp": {
            "value": 34,
            "unit": "C"
        },
        "forecastMintemp": {
            "value": 28,
            "unit": "C"
        },
        "forecastMaxrh": {
            "value": 90,
            "unit": "percent"
        },
        "forecastMinrh": {
            "value": 60,
            "unit": "percent"
        },
        "ForecastIcon": 90,
        "PSR": "低"
    }, {
        "forecastDate": "20230725",
        "week": "星期二",
        "forecastWind": "東至東北風2至3級。",
        "forecastWeather": "部分時間有陽光及酷熱。稍後有幾陣驟雨及狂風雷暴。",
        "forecastMaxtemp": {
            "value": 34,
            "unit": "C"
        },
        "forecastMintemp": {
            "value": 28,
            "unit": "C"
        },
        "forecastMaxrh": {
            "value": 95,
            "unit": "percent"
        },
        "forecastMinrh": {
            "value": 60,
            "unit": "percent"
        },
        "ForecastIcon": 90,
        "PSR": "中低"
    }, {
        "forecastDate": "20230726",
        "week": "星期三",
        "forecastWind": "東至東北風4至5級，離岸間中6級。",
        "forecastWeather": "大致多雲，間中有驟雨，局部地區有狂風雷暴。",
        "forecastMaxtemp": {
            "value": 31,
            "unit": "C"
        },
        "forecastMintemp": {
            "value": 27,
            "unit": "C"
        },
        "forecastMaxrh": {
            "value": 95,
            "unit": "percent"
        },
        "forecastMinrh": {
            "value": 80,
            "unit": "percent"
        },
        "ForecastIcon": 63,
        "PSR": "中高"
    }, {
        "forecastDate": "20230727",
        "week": "星期四",
        "forecastWind": "東至東北風5至6級，離岸達7級。",
        "forecastWeather": "多雲，間中有驟雨，局部地區有雷暴，亦有狂風。",
        "forecastMaxtemp": {
            "value": 30,
            "unit": "C"
        },
        "forecastMintemp": {
            "value": 27,
            "unit": "C"
        },
        "forecastMaxrh": {
            "value": 95,
            "unit": "percent"
        },
        "forecastMinrh": {
            "value": 80,
            "unit": "percent"
        },
        "ForecastIcon": 63,
        "PSR": "高"
    }, {
        "forecastDate": "20230728",
        "week": "星期五",
        "forecastWind": "南至東南風5至6級，初時離岸達7級。",
        "forecastWeather": "多雲，間中有驟雨，局部地區有狂風雷暴。",
        "forecastMaxtemp": {
            "value": 30,
            "unit": "C"
        },
        "forecastMintemp": {
            "value": 27,
            "unit": "C"
        },
        "forecastMaxrh": {
            "value": 95,
            "unit": "percent"
        },
        "forecastMinrh": {
            "value": 80,
            "unit": "percent"
        },
        "ForecastIcon": 63,
        "PSR": "中高"
    }, {
        "forecastDate": "20230729",
        "week": "星期六",
        "forecastWind": "南至東南風5級，離岸間中6級。",
        "forecastWeather": "大致多雲，間中有驟雨，局部地區有狂風雷暴。",
        "forecastMaxtemp": {
            "value": 30,
            "unit": "C"
        },
        "forecastMintemp": {
            "value": 27,
            "unit": "C"
        },
        "forecastMaxrh": {
            "value": 95,
            "unit": "percent"
        },
        "forecastMinrh": {
            "value": 80,
            "unit": "percent"
        },
        "ForecastIcon": 63,
        "PSR": "中"
    }],
    "updateTime": "2023-07-20T16:30:00+08:00",
    "seaTemp": {
        "place": "北角",
        "value": 29,
        "unit": "C",
        "recordTime": "2023-07-20T14:00:00+08:00"
    },
    "soilTemp": [{
        "place": "香港天文台",
        "value": 30.1,
        "unit": "C",
        "recordTime": "2023-07-20T07:00:00+08:00",
        "depth": {
            "unit": "metre",
            "value": 0.5
        }
    }, {
        "place": "香港天文台",
        "value": 30,
        "unit": "C",
        "recordTime": "2023-07-20T07:00:00+08:00",
        "depth": {
            "unit": "metre",
            "value": 1
        }
    }]
}